algebra/__init__.py
algebra/matrices.py
algebra/ntt.py
algebra/polynomials.py
fusion/__init__.py
fusion/fusion.py
fusion_cryptography-0.0.0.dist-info/LICENSE
fusion_cryptography-0.0.0.dist-info/METADATA
fusion_cryptography-0.0.0.dist-info/WHEEL
fusion_cryptography-0.0.0.dist-info/top_level.txt
fusion_cryptography-0.0.0.dist-info/RECORD
