Metadata-Version: 2.1
Name: fusion-cryptography
Version: 0.0.0
Summary: Fusion: highly aggregatable digital signatures using post-quantum lattice cryptography
Home-page: https://github.com/geometry-labs/fusion-cryptography
Author: Geometry Labs
Author-email: info@geometrylabs.io
License: MIT
Keywords: lattice,cryptography,fusion,signatures
Classifier: Intended Audience :: Developers
Classifier: Intended Audience :: Science/Research
Classifier: Intended Audience :: Financial and Insurance Industry
Classifier: Natural Language :: English
Classifier: License :: OSI Approved :: MIT License
Classifier: Programming Language :: Python :: 3 :: Only
Classifier: Programming Language :: Python :: 3
Classifier: Programming Language :: Python :: 3.6
Classifier: Programming Language :: Python :: 3.7
Classifier: Programming Language :: Python :: 3.8
Classifier: Programming Language :: Python :: 3.9
Classifier: Programming Language :: Python :: 3.10
Classifier: Programming Language :: Python :: 3.11
Classifier: Programming Language :: Python :: Implementation :: CPython
Classifier: Programming Language :: Python :: Implementation :: PyPy
Classifier: Programming Language :: Python
Classifier: Topic :: Software Development
Classifier: Topic :: Scientific/Engineering :: Mathematics
Classifier: Topic :: Security :: Cryptography
Classifier: Typing :: Typed
Requires-Python: >=3.6
License-File: LICENSE
